util_common/__init__.py
util_common/_cfg.py
util_common/_log.py
util_common/datetime.py
util_common/decorator.py
util_common/dict_util.py
util_common/downloader.py
util_common/io.py
util_common/io_util.py
util_common/list_util.py
util_common/logger.py
util_common/mongo_util.py
util_common/monitor.py
util_common/package.py
util_common/path.py
util_common/py.typed
util_common/pydantic_util.py
util_common/singleton.py
util_common/sys.py
util_common/uuid.py
util_common/uuid_util.py
util_common-0.6.10.dist-info/licenses/LICENSE.txt
util_common-0.6.10.dist-info/METADATA
util_common-0.6.10.dist-info/WHEEL
util_common-0.6.10.dist-info/top_level.txt
util_common-0.6.10.dist-info/RECORD
