Metadata-Version: 2.4
Name: util_common
Version: 0.6.10
Summary: ...
Author-email: Sheldon Lee <sheldonlee@outlook.com>
Classifier: Programming Language :: Python :: 3
Classifier: Operating System :: OS Independent
Requires-Python: >=3.8
License-File: LICENSE.txt
Provides-Extra: dev
Requires-Dist: twine; extra == "dev"
Requires-Dist: build; extra == "dev"
Requires-Dist: pytest; extra == "dev"
Requires-Dist: mypy; extra == "dev"
Requires-Dist: types-toml; extra == "dev"
Requires-Dist: pre-commit; extra == "dev"
Requires-Dist: pytest-asyncio; extra == "dev"
Dynamic: license-file
